currency_parser/__init__.py
currency_parser/international.py
currency_parser/version.py
currency_parser-0.1.404.dist-info/METADATA
currency_parser-0.1.404.dist-info/WHEEL
currency_parser-0.1.404.dist-info/top_level.txt
currency_parser-0.1.404.dist-info/RECORD
