Metadata-Version: 2.1
Name: currency-parser
Version: 0.1.404
Summary: Currency Value Parser
Home-page: UNKNOWN
Author: Varun Mittal
Author-email: varunmittal@nlpcore.com
License: UNKNOWN
Platform: UNKNOWN
Requires-Dist: setuptools (~=54.2.0)
